MANIFEST.in
README.txt
plonetheme.responsivetheme-configure.zcml
setup.py
docs/HISTORY.txt
docs/INSTALL.txt
docs/LICENSE.GPL
docs/LICENSE.txt
plonetheme/.DS_Store
plonetheme/__init__.py
plonetheme/svn-commit.tmp
plonetheme.responsivetheme.egg-info/PKG-INFO
plonetheme.responsivetheme.egg-info/SOURCES.txt
plonetheme.responsivetheme.egg-info/dependency_links.txt
plonetheme.responsivetheme.egg-info/entry_points.txt
plonetheme.responsivetheme.egg-info/namespace_packages.txt
plonetheme.responsivetheme.egg-info/not-zip-safe
plonetheme.responsivetheme.egg-info/paster_plugins.txt
plonetheme.responsivetheme.egg-info/requires.txt
plonetheme.responsivetheme.egg-info/top_level.txt
plonetheme/responsivetheme/__init__.py
plonetheme/responsivetheme/configure.zcml
plonetheme/responsivetheme/migrations.py
plonetheme/responsivetheme/profiles.zcml
plonetheme/responsivetheme/setuphandlers.py
plonetheme/responsivetheme/skins.zcml
plonetheme/responsivetheme/tests.py
plonetheme/responsivetheme/upgrades.zcml
plonetheme/responsivetheme/Extensions/Install.py
plonetheme/responsivetheme/browser/.DS_Store
plonetheme/responsivetheme/browser/__init__.py
plonetheme/responsivetheme/browser/columncontrol.py
plonetheme/responsivetheme/browser/configure.zcml
plonetheme/responsivetheme/browser/interfaces.py
plonetheme/responsivetheme/browser/viewlet.pt
plonetheme/responsivetheme/browser/viewlets.py
plonetheme/responsivetheme/browser/images/README.txt
plonetheme/responsivetheme/browser/templates/global_sections.pt
plonetheme/responsivetheme/browser/templates/header.pt
plonetheme/responsivetheme/browser/templates/logo.pt
plonetheme/responsivetheme/browser/templates/personal_bar.pt
plonetheme/responsivetheme/browser/templates/searchbox.pt
plonetheme/responsivetheme/locales/README.txt
plonetheme/responsivetheme/profiles/default/.DS_Store
plonetheme/responsivetheme/profiles/default/browserlayer.xml
plonetheme/responsivetheme/profiles/default/cssregistry.xml
plonetheme/responsivetheme/profiles/default/jsregistry.xml
plonetheme/responsivetheme/profiles/default/metadata.xml
plonetheme/responsivetheme/profiles/default/plonetheme.responsivetheme_various.txt
plonetheme/responsivetheme/profiles/default/skins.xml
plonetheme/responsivetheme/profiles/uninstall/.DS_Store
plonetheme/responsivetheme/profiles/uninstall/cssregistry.xml
plonetheme/responsivetheme/profiles/uninstall/jsregistry.xml
plonetheme/responsivetheme/profiles/uninstall/skins.xml
