Metadata-Version: 1.0
Name: plonetheme.responsivetheme
Version: 1.1.4
Summary: An installable theme for Plone 4 that uses a fluid grid system
Home-page: http://svn.plone.org/svn/collective/
Author: WebLion
Author-email: support@weblion.psu.edu
License: GPL
Platform: UNKNOWN
Classifier: Framework :: Plone
Classifier: Programming Language :: Python
